llmteam/__init__.py
llmteam/compat.py
llmteam/contract.py
llmteam/exceptions.py
llmteam/py.typed
llmteam/team.py
llmteam/actions/__init__.py
llmteam/actions/executor.py
llmteam/actions/models.py
llmteam/actions/registry.py
llmteam/actions/handlers/__init__.py
llmteam/actions/handlers/function.py
llmteam/actions/handlers/webhook.py
llmteam/agents/__init__.py
llmteam/agents/base.py
llmteam/agents/config.py
llmteam/agents/factory.py
llmteam/agents/kag_agent.py
llmteam/agents/llm_agent.py
llmteam/agents/orchestrator.py
llmteam/agents/presets.py
llmteam/agents/prompts.py
llmteam/agents/rag_agent.py
llmteam/agents/report.py
llmteam/agents/result.py
llmteam/agents/retry.py
llmteam/agents/state.py
llmteam/agents/types.py
llmteam/api/__init__.py
llmteam/api/app.py
llmteam/api/health.py
llmteam/api/models.py
llmteam/api/websocket.py
llmteam/audit/__init__.py
llmteam/audit/models.py
llmteam/audit/trail.py
llmteam/audit/stores/__init__.py
llmteam/audit/stores/memory.py
llmteam/audit/stores/postgres.py
llmteam/auth/__init__.py
llmteam/auth/apikey.py
llmteam/auth/jwt.py
llmteam/auth/middleware.py
llmteam/auth/oidc.py
llmteam/cli/__init__.py
llmteam/cli/main.py
llmteam/clients/__init__.py
llmteam/clients/circuit_breaker.py
llmteam/clients/graphql.py
llmteam/clients/grpc.py
llmteam/clients/http.py
llmteam/clients/retry.py
llmteam/configuration/__init__.py
llmteam/configuration/models.py
llmteam/configuration/prompts.py
llmteam/configuration/session.py
llmteam/context/__init__.py
llmteam/context/hierarchical.py
llmteam/context/propagation.py
llmteam/context/provider.py
llmteam/context/secure_context.py
llmteam/context/security.py
llmteam/context/visibility.py
llmteam/cost/__init__.py
llmteam/cost/budget.py
llmteam/cost/pricing.py
llmteam/cost/tracker.py
llmteam/engine/__init__.py
llmteam/engine/catalog.py
llmteam/engine/engine.py
llmteam/engine/exceptions.py
llmteam/engine/handlers.py
llmteam/engine/models.py
llmteam/engine/validation.py
llmteam/engine/widget.py
llmteam_ai-5.3.0.dist-info/METADATA
llmteam_ai-5.3.0.dist-info/WHEEL
llmteam_ai-5.3.0.dist-info/entry_points.txt
llmteam_ai-5.3.0.dist-info/licenses/LICENSE
llmteam_ai-5.3.0.dist-info/licenses/NOTICE
llmteam_ai-5.3.0.dist-info/RECORD
