Metadata-Version: 2.4
Name: llmteam-ai
Version: 5.3.0
Summary: Enterprise AI Workflow Runtime - Multi-agent LLM pipelines with security, orchestration, and workflow capabilities
Project-URL: Homepage, https://github.com/KirilinVS/llmteam
Project-URL: Documentation, https://github.com/KirilinVS/llmteam#readme
Project-URL: Repository, https://github.com/KirilinVS/llmteam
Project-URL: Changelog, https://github.com/KirilinVS/llmteam/blob/main/CHANGELOG.md
Project-URL: Issues, https://github.com/KirilinVS/llmteam/issues
Author-email: KirilinVS <LLMTeamai@gmail.com>
License-Expression: Apache-2.0
License-File: LICENSE
License-File: NOTICE
Keywords: agents,ai,enterprise,llm,multi-agent,pipeline,workflow
Classifier: Development Status :: 4 - Beta
Classifier: Intended Audience :: Developers
Classifier: License :: OSI Approved :: Apache Software License
Classifier: Operating System :: OS Independent
Classifier: Programming Language :: Python :: 3
Classifier: Programming Language :: Python :: 3.10
Classifier: Programming Language :: Python :: 3.11
Classifier: Programming Language :: Python :: 3.12
Classifier: Topic :: Scientific/Engineering :: Artificial Intelligence
Classifier: Topic :: Software Development :: Libraries :: Python Modules
Classifier: Typing :: Typed
Requires-Python: >=3.10
Requires-Dist: aiohttp>=3.9.0
Requires-Dist: click>=8.1.0
Provides-Extra: all
Requires-Dist: aiokafka>=0.10.0; extra == 'all'
Requires-Dist: anthropic>=0.8.0; extra == 'all'
Requires-Dist: asyncpg>=0.28.0; extra == 'all'
Requires-Dist: azure-identity>=1.15.0; extra == 'all'
Requires-Dist: azure-keyvault-secrets>=4.7.0; extra == 'all'
Requires-Dist: boto3>=1.28.0; extra == 'all'
Requires-Dist: cryptography>=41.0.0; extra == 'all'
Requires-Dist: fastapi>=0.109.0; extra == 'all'
Requires-Dist: google-cloud-aiplatform>=1.40.0; extra == 'all'
Requires-Dist: gql[aiohttp]>=3.5.0; extra == 'all'
Requires-Dist: grpcio>=1.60.0; extra == 'all'
Requires-Dist: hvac>=2.1.0; extra == 'all'
Requires-Dist: jsonpath-ng>=1.6.0; extra == 'all'
Requires-Dist: jsonschema>=4.20.0; extra == 'all'
Requires-Dist: litellm>=1.20.0; extra == 'all'
Requires-Dist: openai>=1.0.0; extra == 'all'
Requires-Dist: opentelemetry-api>=1.20.0; extra == 'all'
Requires-Dist: opentelemetry-exporter-otlp>=1.20.0; extra == 'all'
Requires-Dist: opentelemetry-sdk>=1.20.0; extra == 'all'
Requires-Dist: pydantic>=2.5.0; extra == 'all'
Requires-Dist: pyjwt>=2.8.0; extra == 'all'
Requires-Dist: redis>=5.0.0; extra == 'all'
Requires-Dist: slowapi>=0.1.9; extra == 'all'
Requires-Dist: structlog>=24.1.0; extra == 'all'
Requires-Dist: uvicorn[standard]>=0.27.0; extra == 'all'
Requires-Dist: websockets>=12.0; extra == 'all'
Provides-Extra: api
Requires-Dist: fastapi>=0.109.0; extra == 'api'
Requires-Dist: pydantic>=2.5.0; extra == 'api'
Requires-Dist: slowapi>=0.1.9; extra == 'api'
Requires-Dist: uvicorn[standard]>=0.27.0; extra == 'api'
Provides-Extra: auth
Requires-Dist: cryptography>=41.0.0; extra == 'auth'
Requires-Dist: pyjwt>=2.8.0; extra == 'auth'
Provides-Extra: aws
Requires-Dist: boto3>=1.28.0; extra == 'aws'
Provides-Extra: azure-secrets
Requires-Dist: azure-identity>=1.15.0; extra == 'azure-secrets'
Requires-Dist: azure-keyvault-secrets>=4.7.0; extra == 'azure-secrets'
Provides-Extra: dev
Requires-Dist: black>=23.9.0; extra == 'dev'
Requires-Dist: mkdocs-material>=9.5.0; extra == 'dev'
Requires-Dist: mypy>=1.5.0; extra == 'dev'
Requires-Dist: pytest-asyncio>=0.21.0; extra == 'dev'
Requires-Dist: pytest-cov>=4.1.0; extra == 'dev'
Requires-Dist: pytest-timeout>=2.2.0; extra == 'dev'
Requires-Dist: pytest-xdist>=3.5.0; extra == 'dev'
Requires-Dist: pytest>=7.4.0; extra == 'dev'
Requires-Dist: ruff>=0.1.0; extra == 'dev'
Provides-Extra: engine
Provides-Extra: graphql
Requires-Dist: gql[aiohttp]>=3.5.0; extra == 'graphql'
Provides-Extra: grpc
Requires-Dist: grpcio-tools>=1.60.0; extra == 'grpc'
Requires-Dist: grpcio>=1.60.0; extra == 'grpc'
Provides-Extra: jsonpath
Requires-Dist: jsonpath-ng>=1.6.0; extra == 'jsonpath'
Provides-Extra: kafka
Requires-Dist: aiokafka>=0.10.0; extra == 'kafka'
Provides-Extra: litellm
Requires-Dist: litellm>=1.20.0; extra == 'litellm'
Provides-Extra: logging
Requires-Dist: structlog>=24.1.0; extra == 'logging'
Provides-Extra: postgres
Requires-Dist: asyncpg>=0.28.0; extra == 'postgres'
Provides-Extra: providers
Requires-Dist: anthropic>=0.8.0; extra == 'providers'
Requires-Dist: openai>=1.0.0; extra == 'providers'
Provides-Extra: redis
Requires-Dist: redis>=5.0.0; extra == 'redis'
Provides-Extra: tracing
Requires-Dist: opentelemetry-api>=1.20.0; extra == 'tracing'
Requires-Dist: opentelemetry-exporter-otlp>=1.20.0; extra == 'tracing'
Requires-Dist: opentelemetry-sdk>=1.20.0; extra == 'tracing'
Provides-Extra: validation
Requires-Dist: jsonschema>=4.20.0; extra == 'validation'
Provides-Extra: vault
Requires-Dist: hvac>=2.1.0; extra == 'vault'
Provides-Extra: vertex
Requires-Dist: google-cloud-aiplatform>=1.40.0; extra == 'vertex'
Provides-Extra: websockets
Requires-Dist: websockets>=12.0; extra == 'websockets'
